rpmdyn.pth
rpmdyn/__init__.py
rpmdyn/_const.py
rpmdyn/_ffi.py
rpmdyn/_keyring.py
rpmdyn/_pth_hook.py
rpmdyn/_rpm.py
rpmdyn/_transaction.py
rpmdyn/rpmdyn.pth
rpmdyn-2025.8.dist-info/licenses/LICENSE
rpmdyn-2025.8.dist-info/METADATA
rpmdyn-2025.8.dist-info/WHEEL
rpmdyn-2025.8.dist-info/top_level.txt
rpmdyn-2025.8.dist-info/RECORD
