Metadata-Version: 2.4
Name: rpmdyn
Version: 2025.8
Summary: Alternative dynamic RPM bindings for Python
Author-email: Rohan McGovern <rohan@mcgovern.id.au>
Maintainer-email: Rohan McGovern <rohan@mcgovern.id.au>
License:                     GNU GENERAL PUBLIC LICENSE
Project-URL: homepage, https://github.com/rohanpm/rpmdyn
Requires-Python: >=3.8
License-File: LICENSE
Requires-Dist: cffi
Dynamic: license-file
